README.md
setup.py
GenomeQAML.egg-info/PKG-INFO
GenomeQAML.egg-info/SOURCES.txt
GenomeQAML.egg-info/dependency_links.txt
GenomeQAML.egg-info/requires.txt
GenomeQAML.egg-info/top_level.txt
genomeqaml/__init__.py
genomeqaml/classify.py
genomeqaml/dataframe.p
genomeqaml/extract_features.py
genomeqaml/model.p
genomeqaml/refseq.msh