Metadata-Version: 1.0
Name: GenomeQAML
Version: 0.0.14
Summary: CFIA OLC Genome Quality Assessment with Machine Learning
Home-page: https://github.com/OLC-LOC-Bioinformatics/GenomeQAML
Author: OLC Bioinformatics
Author-email: adam.koziol@canada.ca
License: MIT
Platform: UNKNOWN
